segments_runner/__init__.py
segments_runner/segments_runner.py
segments_runner/test_data/coco_labels.txt
segments_runner/test_data/det_output_org.jpg
segments_runner/test_data/det_output_seg.jpg
segments_runner/test_data/face.jpg
segments_runner/test_data/grace_hopper.bmp
segments_runner/test_data/imagenet_labels.txt
segments_runner/test_data/inat_bird_labels.txt
segments_runner/test_data/parrot.jpg
segments_runner-1.0.5.dist-info/licenses/LICENSE
segments_runner-1.0.5.dist-info/METADATA
segments_runner-1.0.5.dist-info/WHEEL
segments_runner-1.0.5.dist-info/top_level.txt
segments_runner-1.0.5.dist-info/RECORD
