Metadata-Version: 2.4
Name: segments_runner
Version: 1.0.5
Summary: Run multiple segments of EdgeTPU models in sequence
Author-email: Changhun Han <ehwjs1914@naver.com>
License: MIT License
Project-URL: Homepage, https://github.com/HanChangHun/SegmentsRunner
Project-URL: Repository, https://github.com/HanChangHun/SegmentsRunner
Project-URL: Issues, https://github.com/HanChangHun/SegmentsRunner/issues
Keywords: EdgeTPU,segments,runner
Classifier: Programming Language :: Python :: 3
Classifier: Operating System :: OS Independent
Classifier: License :: OSI Approved :: MIT License
Requires-Python: <3.10,>=3.7
License-File: LICENSE
Requires-Dist: build>=1.1.1
Requires-Dist: numpy<2.0.0,>=1.16.0
Requires-Dist: packaging>=24.0
Requires-Dist: pillow>=9.5.0
Requires-Dist: pip>=24.0
Requires-Dist: twine>=4.0.2
Dynamic: license-file
